rsrc_web/__init__.py
rsrc_web/base.py
rsrc_web/models.py
rsrc_web-0.0.3.dist-info/LICENSE
rsrc_web-0.0.3.dist-info/METADATA
rsrc_web-0.0.3.dist-info/WHEEL
rsrc_web-0.0.3.dist-info/entry_points.txt
rsrc_web-0.0.3.dist-info/top_level.txt
rsrc_web-0.0.3.dist-info/RECORD
