Metadata-Version: 2.1
Name: rsrc-web
Version: 0.0.3
Summary: `rsrc` plugin for working with web resources.
Home-page: https://github.com/lycantropos/rsrc_web/
Author: Azat Ibrakov
Author-email: azatibrakov@gmail.com
License: UNKNOWN
Download-URL: https://github.com/lycantropos/rsrc_web/archive/master.zip
Platform: UNKNOWN
Requires-Python: >=3.5.3
Requires-Dist: memoir (>=0.0.3)
Requires-Dist: reprit (>=0.2.2)
Requires-Dist: requests (>=2.5.0)
Requires-Dist: rsrc (>=0.1.2)
